badexperiment/__init__.py
badexperiment/badexperiment.py
badexperiment/becli.py
badexperiment/hello.py
badexperiment/sheet2yaml.py
badexperiment-0.1.21.dist-info/entry_points.txt
badexperiment-0.1.21.dist-info/WHEEL
badexperiment-0.1.21.dist-info/METADATA
badexperiment-0.1.21.dist-info/RECORD
