Metadata-Version: 2.1
Name: badexperiment
Version: 0.1.21
Summary: see https://github.com/turbomam/badexperiment
Author: Mark A. Miller
Author-email: mamillerpa@gmail.com
Requires-Python: >=3.9,<4.0
Classifier: Programming Language :: Python :: 3
Classifier: Programming Language :: Python :: 3.10
Classifier: Programming Language :: Python :: 3.9
Requires-Dist: click (>=8.0.3,<9.0.0)
Requires-Dist: google-api-python-client
Requires-Dist: google-auth-oauthlib
Requires-Dist: pandas
Requires-Dist: pyyaml
